vatspy_data/__init__.py
vatspy_data/types.py
vatspy_data-1.2.0.dist-info/METADATA
vatspy_data-1.2.0.dist-info/WHEEL
vatspy_data-1.2.0.dist-info/top_level.txt
vatspy_data-1.2.0.dist-info/RECORD
