Metadata-Version: 2.1
Name: vatspy-data
Version: 1.2.0
Summary: python representation of vatspy static data
Author-email: Pavel Vorobyev <aquavitale@yandex.ru>
License: MIT
Project-URL: Source, https://github.com/viert/python-vatspy-data
Keywords: vatspy,vatsim
Requires-Python: >=3.11
Requires-Dist: pydantic
Requires-Dist: requests
Requires-Dist: shapely
